cyndaquil/__init__.py
cyndaquil/cyndaquil.py
cyndaquil/exceptions.py
cyndaquil-1.1.dist-info/LICENSE
cyndaquil-1.1.dist-info/METADATA
cyndaquil-1.1.dist-info/WHEEL
cyndaquil-1.1.dist-info/top_level.txt
cyndaquil-1.1.dist-info/RECORD
