Metadata-Version: 2.1
Name: cyndaquil
Version: 1.1
Summary: Python wrapper for the PokéAPI RESTful api
Home-page: https://github.com/redjordan1202/PyDex
Author: Jordan Del Pilar
Author-email: redjordan123@gmail.com
License: MIT
Classifier: Development Status :: 4 - Beta
Classifier: Intended Audience :: Developers
Classifier: License :: OSI Approved :: MIT License
Classifier: Operating System :: OS Independent
Classifier: Programming Language :: Python :: 3 :: Only
Classifier: Programming Language :: Python :: 3.10
Classifier: Topic :: Internet
Classifier: Topic :: Software Development :: Libraries
Classifier: Topic :: Software Development :: Libraries :: Python Modules
Classifier: Topic :: Utilities
License-File: LICENSE
Requires-Dist: requests
